ambigram/__init__.py
ambigram/_version.py
ambigram/ambigram.py
ambigram/utils.py
ambigram-0.0.29.dist-info/licenses/COPYING
ambigram-0.0.29.dist-info/licenses/LICENSE
ambigram-0.0.29.dist-info/METADATA
ambigram-0.0.29.dist-info/WHEEL
ambigram-0.0.29.dist-info/entry_points.txt
ambigram-0.0.29.dist-info/top_level.txt
ambigram-0.0.29.dist-info/RECORD
