Metadata-Version: 2.4
Name: ambigram
Version: 0.0.29
Summary: 3D Ambigram Generation using Cadquery
Author-email: sivefunc <sivefunc@tuta.io>
License: ambigram <-> 3D Ambigram Generation using Cadquery
Project-URL: Homepage, https://github.com/Sivefunc/ambigram
Classifier: License :: OSI Approved :: GNU General Public License v3 (GPLv3)
Classifier: Programming Language :: Python
Classifier: Programming Language :: Python :: 3
Requires-Python: >=3.11
License-File: LICENSE
License-File: COPYING
Requires-Dist: cadquery
Provides-Extra: dev
Requires-Dist: pylint; extra == "dev"
Provides-Extra: keywords
Requires-Dist: linux; extra == "keywords"
Requires-Dist: python3; extra == "keywords"
Requires-Dist: ambigram; extra == "keywords"
Requires-Dist: cadquery; extra == "keywords"
Dynamic: license-file
